bespon/__init__.py
bespon/ast.py
bespon/astnodes.py
bespon/coding.py
bespon/decoding.py
bespon/dumping.py
bespon/encoding.py
bespon/erring.py
bespon/escape.py
bespon/fmtversion.py
bespon/grammar.py
bespon/load_types.py
bespon/loading.py
bespon/re_patterns.py
bespon/roundtrip.py
bespon/tooling.py
bespon/version.py
bespon-0.7.0.dist-info/CHANGELOG.md
bespon-0.7.0.dist-info/LICENSE.txt
bespon-0.7.0.dist-info/METADATA
bespon-0.7.0.dist-info/WHEEL
bespon-0.7.0.dist-info/top_level.txt
bespon-0.7.0.dist-info/RECORD
