Metadata-Version: 2.1
Name: bespon
Version: 0.7.0
Summary: Python library for BespON
Author-email: "Geoffrey M. Poore" <gpoore@gmail.com>
License: Copyright 2016-2017 Geoffrey M. Poore
Project-URL: homepage, https://bespon.org/
Project-URL: repository, http://github.com/gpoore/bespon_py
Project-URL: changelog, https://github.com/gpoore/bespon_py/blob/master/CHANGELOG.md
Keywords: configuration,serialization,interchange
Classifier: Development Status :: 4 - Beta
Classifier: Intended Audience :: Developers
Classifier: Intended Audience :: End Users/Desktop
Classifier: Intended Audience :: Information Technology
Classifier: Intended Audience :: Science/Research
Classifier: Intended Audience :: System Administrators
Classifier: License :: OSI Approved :: BSD License
Classifier: Operating System :: OS Independent
Classifier: Programming Language :: Python
Classifier: Topic :: Utilities
Requires-Python: >=3.7
License-File: LICENSE.txt
License-File: CHANGELOG.md
